oauth_dcr/views.py
django_oauth_toolkit_dcr-0.1.0.dist-info/LICENCE.md
django_oauth_toolkit_dcr-0.1.0.dist-info/METADATA
django_oauth_toolkit_dcr-0.1.0.dist-info/WHEEL
django_oauth_toolkit_dcr-0.1.0.dist-info/RECORD
