Metadata-Version: 2.3
Name: django-oauth-toolkit-dcr
Version: 0.1.0
Summary: An extension to django oauth toolkit to support Dynamic Client Registration RFC7591
License: MIT
Keywords: django,oauth,dynamic client registration,rfc7591
Author: Omar BENHAMID
Author-email: omar.benhamid@smart-gts.com
Requires-Python: >=3.10
Classifier: Framework :: Django
Classifier: Framework :: Django :: 4
Classifier: Framework :: Django :: 5
Classifier: Programming Language :: Python :: 3
Classifier: License :: OSI Approved :: MIT License
Requires-Dist: django (>=4.0)
Requires-Dist: django-oauth-toolkit (>=3.0.1,<4.0.0)
